Metadata-Version: 1.1
Name: swamper
Version: 0.1
Summary: Swamper is a simple interface to clean input data and turn this data into objects.
Home-page: https://github.com/wearespindle/swamper
Author: Devhouse Spindle
Author-email: opensource@wearespindle.com
License: MIT License
Platform: UNKNOWN
Classifier: Development Status :: 3 - Alpha
Classifier: Intended Audience :: Developers
Classifier: License :: OSI Approved :: MIT License
Classifier: Programming Language :: Python :: 2.7
